skrules/__init__.py
skrules/rule.py
skrules/skope_rules.py
skrules/datasets/__init__.py
skrules/datasets/credit_data.py
skrules/tests/__init__.py
skrules/tests/test_common.py
skrules/tests/test_rule.py
skrules/tests/test_skope_rules.py
skope_rules-1.0.1.dist-info/AUTHORS.rst
skope_rules-1.0.1.dist-info/COPYING
skope_rules-1.0.1.dist-info/METADATA
skope_rules-1.0.1.dist-info/WHEEL
skope_rules-1.0.1.dist-info/top_level.txt
skope_rules-1.0.1.dist-info/RECORD
