Metadata-Version: 2.1
Name: skope-rules
Version: 1.0.1
Summary: Machine Learning with Interpretable Rules
Home-page: https://github.com/scikit-learn-contrib/skope-rules
Author: see AUTHORS.rst
Author-email: UNKNOWN
License: BSD 3 clause
Keywords: learning with rules,interpretable machine learning
Platform: UNKNOWN
Requires-Dist: numpy (>=1.10.4)
Requires-Dist: scikit-learn (>=0.17.1)
Requires-Dist: scipy (>=0.17.0)
Requires-Dist: pandas (>=0.18.1)
